SchoolSDK/__init__.py
SchoolSDK/client.py
SchoolSDK/config.py
SchoolSDK/exceptions.py
SchoolSDK/utils.py
SchoolSDK/tests/__init__.py
SchoolSDK/tests/test_client.py
SchoolSDK/tests/test_utils.py
valschoolsdk-0.1.3.dist-info/METADATA
valschoolsdk-0.1.3.dist-info/WHEEL
valschoolsdk-0.1.3.dist-info/top_level.txt
valschoolsdk-0.1.3.dist-info/RECORD
