Metadata-Version: 2.1
Name: valschoolsdk
Version: 0.1.3
Summary: A well-structured Python SDK template for school
Author: ChideraVal
Author-email: chideraval@example.com
License: MIT
